wraeblast/cmd.py
wraeblast/constants.py
wraeblast/errors.py
wraeblast/filtering/colors.py
wraeblast/filtering/elements.py
wraeblast/filtering/parsers/extended/__init__.py
wraeblast/filtering/parsers/extended/config.py
wraeblast/filtering/parsers/extended/env.py
wraeblast/filtering/parsers/standard/__init__.py
wraeblast/filtering/parsers/standard/poe_filter_grammar.lark
wraeblast/filtering/parsers/standard/transformers.py
wraeblast/filtering/serializers/standard.py
wraeblast/insights.py
wraeblast/logging_.py
wraeblast/types.py
wraeblast-0.3.0.dist-info/entry_points.txt
wraeblast-0.3.0.dist-info/LICENSE
wraeblast-0.3.0.dist-info/WHEEL
wraeblast-0.3.0.dist-info/METADATA
wraeblast-0.3.0.dist-info/RECORD
