Metadata-Version: 2.1
Name: wraeblast
Version: 0.3.0
Summary: Tools for Path of Exile filter generation and economy data analysis.
License: MIT
Author: David Gidwani
Author-email: david.gidwani@gmail.com
Requires-Python: >=3.9,<3.11
Classifier: License :: OSI Approved :: MIT License
Classifier: Programming Language :: Python :: 3
Classifier: Programming Language :: Python :: 3.10
Classifier: Programming Language :: Python :: 3.9
Provides-Extra: tts
Requires-Dist: Jinja2 (>=3.0.1,<4.0.0)
Requires-Dist: aiohttp (>=3.7.4,<4.0.0)
Requires-Dist: backoff (>=1.11.1,<2.0.0)
Requires-Dist: boto3 (>=1.18.26,<2.0.0)
Requires-Dist: cachetools (>=4.2.2,<5.0.0)
Requires-Dist: cleo (>=0.8.1,<0.9.0)
Requires-Dist: colorcet (>=2.0.6,<3.0.0)
Requires-Dist: colormath (>=3.0.0,<4.0.0)
Requires-Dist: colour (>=0.1.5,<0.2.0)
Requires-Dist: glom (>=20.11.0,<21.0.0)
Requires-Dist: inflection (>=0.5.1,<0.6.0)
Requires-Dist: lark (>=0.11.3,<0.12.0)
Requires-Dist: matplotlib (>=3.4.2,<4.0.0)
Requires-Dist: mergedeep (>=1.3.4,<2.0.0)
Requires-Dist: numpy (>=1.22.2,<2.0.0)
Requires-Dist: palettable (>=3.3.0,<4.0.0)
Requires-Dist: pandas (>=1.3.2,<2.0.0)
Requires-Dist: pandera (>=0.7.1,<0.8.0)
Requires-Dist: pydantic (>=1.8.2,<2.0.0)
Requires-Dist: pydub (>=0.25.1,<0.26.0)
Requires-Dist: python-json-logger (>=2.0.1,<3.0.0)
Requires-Dist: pyttsx3 (>=2.90,<3.0); extra == "tts"
Requires-Dist: requests (>=2.25.1,<3.0.0)
Requires-Dist: ruamel.yaml (>=0.17.5,<0.18.0)
Requires-Dist: structlog (>=21.1.0,<22.0.0)
Requires-Dist: tables (>=3.7.0,<4.0.0)
Requires-Dist: uplink[aiohttp] (>=0.9.6,<0.10.0)
